HISTORY.rst
LICENSE
MANIFEST.in
README.rst
accept.py
setup.py
accept.egg-info/PKG-INFO
accept.egg-info/SOURCES.txt
accept.egg-info/dependency_links.txt
accept.egg-info/not-zip-safe
accept.egg-info/top_level.txt