Metadata-Version: 1.1
Name: accept
Version: 0.1.0
Summary: Parse and order a HTTP Accept header.
Home-page: http://github.com/rhyselsmore/accept
Author: Rhys Elsmore
Author-email: me@rhys.io
License: Copyright (c) 2015, Rhys Elsmore <me@rhys.io>
